odoo/addons/web_time_range_menu_custom/README.rst
odoo/addons/web_time_range_menu_custom/__init__.py
odoo/addons/web_time_range_menu_custom/__manifest__.py
odoo/addons/web_time_range_menu_custom/i18n/es.po
odoo/addons/web_time_range_menu_custom/i18n/it.po
odoo/addons/web_time_range_menu_custom/i18n/web_time_range_menu_custom.pot
odoo/addons/web_time_range_menu_custom/readme/CONTRIBUTORS.md
odoo/addons/web_time_range_menu_custom/readme/DESCRIPTION.md
odoo/addons/web_time_range_menu_custom/readme/USAGE.md
odoo/addons/web_time_range_menu_custom/static/description/custom_period_option.png
odoo/addons/web_time_range_menu_custom/static/description/icon.png
odoo/addons/web_time_range_menu_custom/static/description/index.html
odoo/addons/web_time_range_menu_custom/static/src/js/date_selector.esm.js
odoo/addons/web_time_range_menu_custom/static/src/js/dates.esm.js
odoo/addons/web_time_range_menu_custom/static/src/js/search_bar_menu.esm.js
odoo/addons/web_time_range_menu_custom/static/src/scss/web_time_range_menu_custom.scss
odoo/addons/web_time_range_menu_custom/static/src/xml/date_selector.xml
odoo/addons/web_time_range_menu_custom/static/src/xml/search_bar_menu.xml
odoo_addon_web_time_range_menu_custom-17.0.1.0.0.5.dist-info/METADATA
odoo_addon_web_time_range_menu_custom-17.0.1.0.0.5.dist-info/WHEEL
odoo_addon_web_time_range_menu_custom-17.0.1.0.0.5.dist-info/top_level.txt
odoo_addon_web_time_range_menu_custom-17.0.1.0.0.5.dist-info/RECORD
